cfcontext.py
cfcontext-1.2.dist-info/METADATA
cfcontext-1.2.dist-info/WHEEL
cfcontext-1.2.dist-info/top_level.txt
cfcontext-1.2.dist-info/RECORD
